tournament_reranker/__init__.py
tournament_reranker/api.py
tournament_reranker/grouping.py
tournament_reranker/parsing.py
tournament_reranker/prompts.py
tournament_reranker/pyramid.py
tournament_reranker/types.py
tournament_reranker/validating.py
tournament_reranker/adapters/__init__.py
tournament_reranker/adapters/openai_chat.py
tournament_reranker-0.2.0.dist-info/METADATA
tournament_reranker-0.2.0.dist-info/WHEEL
tournament_reranker-0.2.0.dist-info/RECORD
