Metadata-Version: 2.4
Name: tournament-reranker
Version: 0.2.0
Summary: LLM reranking via a tournament/pyramid strategy.
Requires-Python: >=3.10
Requires-Dist: openai>=2.14.0
